ULA.v
module ULA (input         clk,
			input  [0:3]  inputULA, 
			input  [0:31] a,
			input  [0:31] b,
			output reg [0:31] outputULA);
	always @(posedge clk) begin
	   	case(inputULA)
			4'b0010: //Operação "Add"
				outputULA <= a + b;
			4'b0110: //Operação "Sub"
				outputULA <= a - b;
			4'b0000: //Operação "And"
				outputULA <= a & b;
			4'b0001: //Operação "Or"
				outputULA <= a | b;
			4'b0111: //Operação "Slt"
				begin
					if(a < b) begin
						outputULA <= 32'h1;
					end else begin 
						outputULA <= 32'h0;
					end
				end
			default://Se a entrada não bater com nada nenhuma operação será realizada
				outputULA <= 32'hx;
		endcase
	end
endmodule

ULAControl.v
module ULAControl(input            clk,
			      input      [0:1] OpALU,
				  input      [0:5] funct,
				  output reg [0:3] inputALU);
		always @(clk) begin
			case(OpALU)
				2'b00://Lw ou SW
					inputALU <= 4'b0010;
				2'b01://Beq
					inputALU <= 4'b0110;
				2'b10://Tipo R
					begin
						case(funct)
							6'b100000: //Operação "Add"
								inputALU <= 4'b0010;
							6'b100010: //Operação "Sub"
								inputALU <= 4'b0110;
							6'b100100: //Operação "And"
								inputALU <= 4'b0000;
							6'b100101: //Operação "Or"
								inputALU <= 4'b0001;
							6'b101010: //Operação "Slt"
								inputALU <= 4'b0111;
							default://Se a entrada não bater com nada nenhuma operação será realizada
								inputALU <= 4'bxxxx;
						endcase
					end
				default:
					inputALU <= 4'bxxxx;
			endcase 
		end
endmodule

MIPS.v
`include "ULA.v"
`include "ULAControl.v"

module MIPS(input             clk,
			input      [0:1]  OpALU,
			input      [0:5]  funct,
			input      [0:31] a,
			input      [0:31] b,
			output     [0:31] outputULA);
	
	
	wire [0:3] inputALU;
	
	//Instância do módulo ULAControl passando o mesmo clk
	ULAControl ULAControl(
		.clk(clk),
		.OpALU(OpALU),
		.funct(funct),
		.inputALU(inputALU)
	);
	
	//Instância do módulo ULA passando o mesmo clk
	ULA ULA(
		.clk(clk),
		.inputULA(inputALU),
		.a(a),
		.b(b),
		.outputULA(outputULA)
	);

endmodule

MIPS_tb.v
`include "MIPS.v"

module tb;
	
	reg         clk;
	reg  [0:1]  OpALU;
	reg  [0:5]  funct;
	reg  [0:31] a;
	reg  [0:31] b;
	wire [0:31] outputULA;
	
	initial begin
		
		$monitor("clk=%b, OpALU=%b, funct=%b, a=%b, b=%b, outputULA=%b", clk, OpALU, funct, a, b, outputULA);
		$dumpfile("MIPS.vcd");
		$dumpvars(0, tb);
		
		clk = 0;
		
		
		//LW ou SW resultado 000...110
		OpALU = 2'b00;
		funct = 6'b000000;
		a = 32'b00000000000000000000000000000011;
		b = 32'b00000000000000000000000000000011;
		
		#2
		
		//ADD resultado 000...100
		OpALU = 2'b10;
		funct = 6'b100000;
		a = 32'b00000000000000000000000000000001;
		b = 32'b00000000000000000000000000000011;
		
		#2
		
		//SUB resultado 000...010
		OpALU = 2'b10;
		funct = 6'b100010;
		a = 32'b00000000000000000000000000000011;
		b = 32'b00000000000000000000000000000001;
		
		#2
		
		//AND resultado 000...001
		OpALU = 2'b10;
		funct = 6'b100100;
		a = 32'b00000000000000000000000000000011;
		b = 32'b00000000000000000000000000000001;
		
		#2
		
		//OR resultado 000.011
		OpALU = 2'b10;
		funct = 6'b100101;
		a = 32'b00000000000000000000000000000011;
		b = 32'b00000000000000000000000000000001;
		
		#2
		
		//SLT resultado 000...001
		OpALU = 2'b10;
		funct = 6'b101010;
		a = 32'b00000000000000000000000000000001;
		b = 32'b00000000000000000000000000000011;
		
		
		#2 $finish;
	end
	
	always begin
		#1 clk = !clk;
	end
	
	MIPS MIPS_tb(
		.clk(clk),
		.OpALU(OpALU),
		.funct(funct),
		.a(a),
		.b(b),
		.outputULA(outputULA)
	);
endmodule

MIPS.vcd
$date
	Tue Aug 01 20:01:40 2023
$end
$version
	Icarus Verilog
$end
$timescale
	1s
$end
$scope module tb $end
$var wire 32 ! outputULA [0:31] $end
$var reg 2 " OpALU [0:1] $end
$var reg 32 # a [0:31] $end
$var reg 32 $ b [0:31] $end
$var reg 1 % clk $end
$var reg 6 & funct [0:5] $end
$scope module MIPS_tb $end
$var wire 2 ' OpALU [0:1] $end
$var wire 32 ( a [0:31] $end
$var wire 32 ) b [0:31] $end
$var wire 1 % clk $end
$var wire 6 * funct [0:5] $end
$var wire 32 + outputULA [0:31] $end
$var wire 4 , inputALU [0:3] $end
$scope module ULA $end
$var wire 32 - a [0:31] $end
$var wire 32 . b [0:31] $end
$var wire 1 % clk $end
$var wire 4 / inputULA [0:3] $end
$var reg 32 0 outputULA [0:31] $end
$upscope $end
$scope module ULAControl $end
$var wire 2 1 OpALU [0:1] $end
$var wire 1 % clk $end
$var wire 6 2 funct [0:5] $end
$var reg 4 3 inputALU [0:3] $end
$upscope $end
$upscope $end
$upscope $end
$enddefinitions $end
$comment Show the parameter values. $end
$dumpall
$end
#0
$dumpvars
b10 3
b0 2
b0 1
bx 0
b10 /
b11 .
b11 -
b10 ,
bx +
b0 *
b11 )
b11 (
b0 '
b0 &
0%
b11 $
b11 #
b0 "
bx !
$end
#1
b110 !
b110 +
b110 0
1%
#2
0%
b1 #
b1 (
b1 -
b100000 &
b100000 *
b100000 2
b10 "
b10 '
b10 1
#3
b100 !
b100 +
b100 0
1%
#4
b110 ,
b110 /
b110 3
0%
b1 $
b1 )
b1 .
b11 #
b11 (
b11 -
b100010 &
b100010 *
b100010 2
#5
b10 !
b10 +
b10 0
1%
#6
b0 ,
b0 /
b0 3
0%
b100100 &
b100100 *
b100100 2
#7
b1 !
b1 +
b1 0
1%
#8
b1 ,
b1 /
b1 3
0%
b100101 &
b100101 *
b100101 2
#9
b11 !
b11 +
b11 0
1%
#10
b111 ,
b111 /
b111 3
0%
b11 $
b11 )
b11 .
b1 #
b1 (
b1 -
b101010 &
b101010 *
b101010 2
#11
b1 !
b1 +
b1 0
1%
